django_admin_object_button/__init__.py
django_admin_object_button/admin.py
django_admin_object_button/apps.py
django_admin_object_button/decorators.py
django_admin_object_button/models.py
django_admin_object_button/tests.py
django_admin_object_button/views.py
django_admin_object_button/migrations/__init__.py
django_admin_object_button-0.0.1.dist-info/METADATA
django_admin_object_button-0.0.1.dist-info/WHEEL
django_admin_object_button-0.0.1.dist-info/top_level.txt
django_admin_object_button-0.0.1.dist-info/RECORD
